seconohe/__init__.py
seconohe/_ansi.py
seconohe/apply_mask.py
seconohe/bti.py
seconohe/color.py
seconohe/comfy_node_action.py
seconohe/comfy_notification.py
seconohe/downloader.py
seconohe/logger.py
seconohe/misc.py
seconohe/register_nodes.py
seconohe/torch.py
seconohe/foreground_estimation/__init__.py
seconohe/foreground_estimation/affce.py
seconohe/foreground_estimation/fmlfe.py
seconohe/foreground_estimation/fmlfe_cupy.py
seconohe/foreground_estimation/fmlfe_numba.py
seconohe/foreground_estimation/fmlfe_pyopencl.py
seconohe/foreground_estimation/fmlfe_torch.py
seconohe-1.0.5.dist-info/licenses/LICENSE
seconohe-1.0.5.dist-info/METADATA
seconohe-1.0.5.dist-info/WHEEL
seconohe-1.0.5.dist-info/top_level.txt
seconohe-1.0.5.dist-info/RECORD
