Metadata-Version: 2.4
Name: seconohe
Version: 1.0.5
Summary: SET's ComfyUI Node Helpers
Author-email: "Salvador E. Tropea" <stropea@inti.gob.ar>
License-Expression: GPL-3.0-or-later
Project-URL: repository, https://github.com/set-soft/seconohe
Project-URL: documentation, https://set-soft.github.io/seconohe/seconohe.html
Classifier: Programming Language :: Python :: 3
Classifier: Operating System :: OS Independent
Requires-Python: >=3.8
License-File: LICENSE
Requires-Dist: tqdm
Provides-Extra: dev
Requires-Dist: pytest; extra == "dev"
Requires-Dist: pdoc; extra == "dev"
Requires-Dist: mypy; extra == "dev"
Provides-Extra: better-dl
Requires-Dist: requests; extra == "better-dl"
Provides-Extra: better-color
Requires-Dist: colorama; extra == "better-color"
Dynamic: license-file
